etpclient/__init__.py
etpclient/etp/__init__.py
etpclient/etp/connection_register.py
etpclient/etp/etp_data_bridge.py
etpclient/etp/etp_notifyer.py
etpclient/etp/h5_handler.py
etpclient/etp/hsds_bridge.py
etpclient/etp/requester.py
etpclient/etp/serverprotocols.py
etpclient/main.py
etpclient/utils.py
etpclient/websocket_manager.py
etpclient-0.0.3.dist-info/LICENSE
etpclient-0.0.3.dist-info/METADATA
etpclient-0.0.3.dist-info/WHEEL
etpclient-0.0.3.dist-info/entry_points.txt
etpclient-0.0.3.dist-info/RECORD
