Metadata-Version: 2.1
Name: etpclient
Version: 0.0.3
Summary: ETP client
Home-page: http://www.geosiris.com
License: Apache-2.0
Keywords: ETP
Author: Valentin Gauthier
Author-email: valentin.gauthier@geosiris.com
Maintainer: Valentin Gauthier
Maintainer-email: valentin.gauthier@geosiris.com
Requires-Python: >=3.9,<4.0
Classifier: Development Status :: 4 - Beta
Classifier: Environment :: Web Environment
Classifier: Intended Audience :: Developers
Classifier: Intended Audience :: Information Technology
Classifier: License :: OSI Approved :: Apache Software License
Classifier: Operating System :: OS Independent
Classifier: Programming Language :: Python
Classifier: Programming Language :: Python :: 3
Classifier: Programming Language :: Python :: 3.9
Classifier: Programming Language :: Python :: 3.10
Classifier: Programming Language :: Python :: 3.11
Classifier: Programming Language :: Python :: 3.8
Classifier: Topic :: Internet
Classifier: Topic :: Internet :: WWW/HTTP
Classifier: Topic :: Software Development
Classifier: Topic :: Software Development :: Libraries
Classifier: Topic :: Software Development :: Libraries :: Application Frameworks
Classifier: Topic :: Software Development :: Libraries :: Python Modules
Classifier: Typing :: Typed
Requires-Dist: etpproto (>=1.0.2,<2.0.0)
Requires-Dist: etptypes (>=1.0.1,<2.0.0)
Requires-Dist: h5py (>=3.7.0,<4.0.0)
Requires-Dist: ipykernel (>=6.5.1,<7.0.0)
Requires-Dist: lxml (>=4.6.3,<5.0.0)
Requires-Dist: requests (>=2.25.1,<3.0.0)
Requires-Dist: websocket-client (>=1.0.0,<2.0.0)
Requires-Dist: xmljson (>=0.2.1,<0.3.0)
Project-URL: Repository, https://github.com/geosiris-technologies/etpclient-python
